cyberfusion/FileSupport/__init__.py
cyberfusion/FileSupport/encryption.py
cyberfusion/FileSupport/exceptions.py
python3_cyberfusion_file_support-1.8.dist-info/METADATA
python3_cyberfusion_file_support-1.8.dist-info/WHEEL
python3_cyberfusion_file_support-1.8.dist-info/top_level.txt
python3_cyberfusion_file_support-1.8.dist-info/RECORD
