Metadata-Version: 2.4
Name: python3-cyberfusion-file-support
Version: 1.8
Summary: Library for idempotent writing to files.
Author-email: Cyberfusion <support@cyberfusion.io>
Project-URL: Source, https://github.com/CyberfusionIO/python3-cyberfusion-file-support
Requires-Dist: python3-cyberfusion-common~=2.12
Requires-Dist: python3-cyberfusion-queue-support~=3.3
